hypothesis_array.py
hypothesis_array_api-0.1.2.dist-info/LICENSE.txt
hypothesis_array_api-0.1.2.dist-info/WHEEL
hypothesis_array_api-0.1.2.dist-info/METADATA
hypothesis_array_api-0.1.2.dist-info/RECORD
