Metadata-Version: 2.1
Name: hypothesis-array-api
Version: 0.1.2
Summary: Hypothesis strategies for Array API libraries
Home-page: https://github.com/honno/hypothesis-array-api
License: MPL-2.0
Author: Matthew Barber
Author-email: quitesimplymatt@gmail.com
Requires-Python: >=3.7,<4.0
Classifier: Framework :: Hypothesis
Classifier: License :: OSI Approved
Classifier: Programming Language :: Python :: 3
Classifier: Programming Language :: Python :: 3.7
Classifier: Programming Language :: Python :: 3.8
Classifier: Programming Language :: Python :: 3.9
Provides-Extra: docs
Requires-Dist: hypothesis (>=6.14.1,<7.0.0)
Requires-Dist: sphinx (>=3,<4); extra == "docs"
Project-URL: Repository, https://github.com/honno/hypothesis-array-api
